libcoveocds/__init__.py
libcoveocds/__main__.py
libcoveocds/api.py
libcoveocds/common_checks.py
libcoveocds/config.py
libcoveocds/exceptions.py
libcoveocds/schema.py
libcoveocds/util.py
libcoveocds/lib/__init__.py
libcoveocds/lib/additional_checks.py
libcoveocds/lib/api.py
libcoveocds/lib/common_checks.py
libcoveocds-0.17.0.dist-info/LICENSE
libcoveocds-0.17.0.dist-info/METADATA
libcoveocds-0.17.0.dist-info/WHEEL
libcoveocds-0.17.0.dist-info/entry_points.txt
libcoveocds-0.17.0.dist-info/top_level.txt
libcoveocds-0.17.0.dist-info/RECORD
