Metadata-Version: 2.1
Name: libcoveocds
Version: 0.17.0
Summary: A data review library for the Open Contracting Data Standard (OCDS)
Author-email: Open Contracting Partnership and Open Data Services Co-operative Limited <data@open-contracting.org>
License: AGPL-3.0-or-later
Project-URL: Homepage, https://github.com/open-contracting/lib-cove-ocds
Classifier: License :: OSI Approved :: GNU Affero General Public License v3 or later (AGPLv3+)
Classifier: Operating System :: MacOS
Classifier: Operating System :: POSIX :: Linux
Classifier: Programming Language :: Python :: 3.9
Classifier: Programming Language :: Python :: 3.10
Classifier: Programming Language :: Python :: 3.11
Classifier: Programming Language :: Python :: 3.12
Classifier: Programming Language :: Python :: Implementation :: CPython
License-File: LICENSE
Requires-Dist: click
Requires-Dist: jsonref >=1
Requires-Dist: jsonschema >=4.18
Requires-Dist: libcove >=0.32
Requires-Dist: ocdsextensionregistry >=0.3.4
Requires-Dist: referencing
Requires-Dist: requests
Provides-Extra: perf
Requires-Dist: orjson ; extra == 'perf'
Provides-Extra: test
Requires-Dist: coverage ; extra == 'test'
Requires-Dist: pytest ; extra == 'test'
Provides-Extra: web
Requires-Dist: bleach >=6 ; extra == 'web'
Requires-Dist: django ; extra == 'web'
Requires-Dist: markdown-it-py ; extra == 'web'
